pornhub/__init__.py
pornhub/client.py
pornhub/response_codes.py
pornhub_api_client-0.1.5.dist-info/entry_points.txt
pornhub_api_client-0.1.5.dist-info/LICENSE
pornhub_api_client-0.1.5.dist-info/WHEEL
pornhub_api_client-0.1.5.dist-info/METADATA
pornhub_api_client-0.1.5.dist-info/RECORD
