Metadata-Version: 2.1
Name: pornhub-api-client
Version: 0.1.5
Summary: Simple lib to work with pornhub API
Author: Misha Bystrov
Author-email: drudkhmisha@gmail.com
Requires-Python: >=3.8,<4.0
Classifier: Programming Language :: Python :: 3
Classifier: Programming Language :: Python :: 3.8
Classifier: Programming Language :: Python :: 3.9
Classifier: Programming Language :: Python :: 3.10
Requires-Dist: requests2 (>=2.16.0,<3.0.0)
